[
       {
        "id": "1",
        "nombre" : "cerveza quilmes clásica 473cc pack x6 unidades",
        "precio" : "9675",
        "img" : "./cerveza.png",
        "cantidad": 0,
        "tipo": "cerveza",
        "cargando": false
        },
        {
        "id": "2",
        "nombre" : "vino toro tinto en caja 1Lt",
        "precio" : "2200",
        "img" : "2.png",
        "cantidad": 0,
        "tipo": "vino",
        "cargando": false
        },
        {
        "id": "3",
        "nombre" : "cerveza quilmes clásica 473cc pack x6 unidades",
        "precio" : "1300",
        "img" : "./cerveza02.png",
        "cantidad": 0,
        "tipo": "cerveza",
        "cargando": false
        },
        {
        "id": "4",
        "nombre" : "vino toro blanco en caja 1lt",
        "precio" : "2000",
        "img" : "./1.png",
        "cantidad": 0,
        "tipo": "vino",
        "cargando": false
        },
        {
        "id": "6",
        "nombre" : "fernet branca 75ml",
        "precio" : "22000",
        "img" : "./4.png",
        "cantidad": 0,
        "tipo": "fernet",
        "cargando": false
        },
        {
        "id": "7",
        "nombre" : "fernet buhero 75ml",
        "precio" : "20000",
        "img" : "3.png",
        "cantidad": 0,
        "tipo": "fernet",
        "cargando": false
        },
        {
        "id": "8",
        "nombre" : "fernet 1882 75ml",
        "precio" : "17000",
        "img" : "5.png",
        "cantidad": 0,
        "tipo": "fernet",
        "cargando": false
        }
        ,
        {
        "id": "8",
        "nombre" : "cerveza imperial golden lata 700cc",
        "precio" : "2000",
        "img" : "6.png",
        "cantidad": 0,
        "tipo": "cerveza",
        "cargando": false
        }
        ,
        {
        "id": "8",
        "nombre" : "vodka smirnoff clasico 75cc",
        "precio" : "20000",
        "img" : "7.png",
        "cantidad": 0,
        "tipo": "vodka",
        "cargando": false
        }
]
